heliumapipy/__init__.py
heliumapipy/api.py
heliumapipy-1.6.dist-info/LICENSE
heliumapipy-1.6.dist-info/METADATA
heliumapipy-1.6.dist-info/WHEEL
heliumapipy-1.6.dist-info/top_level.txt
heliumapipy-1.6.dist-info/RECORD
