Metadata-Version: 2.1
Name: heliumapipy
Version: 1.6
Summary: Unofficial api for Helium Explorer
Home-page: https://github.com/mikhailkrasulin/HeliumAPI-Python
Author: mkrasulin2020
Author-email: mkrasulin2020@gmail.com
License: UNKNOWN
Project-URL: Bug Tracker, https://github.com/mikhailkrasulin/HeliumAPI-Python/issues
Platform: UNKNOWN
Classifier: Programming Language :: Python :: 3
Classifier: License :: OSI Approved :: MIT License
Classifier: Operating System :: OS Independent
Requires-Python: >=3.6
License-File: LICENSE
